geoviews/.eslintrc.js
geoviews/__init__.py
geoviews/__main__.py
geoviews/__version.py
geoviews/_version.py
geoviews/_warnings.py
geoviews/annotators.py
geoviews/bokeh.ext.json
geoviews/feature.py
geoviews/index.ts
geoviews/links.py
geoviews/package-lock.json
geoviews/package.json
geoviews/streams.py
geoviews/tile_sources.py
geoviews/tsconfig.json
geoviews/util.py
geoviews/data/__init__.py
geoviews/data/geom_dict.py
geoviews/data/geopandas.py
geoviews/data/iris.py
geoviews/element/__init__.py
geoviews/element/comparison.py
geoviews/element/geo.py
geoviews/examples/Homepage.ipynb
geoviews/examples/conftest.py
geoviews/examples/datasets.yml
geoviews/examples/assets/cities.csv
geoviews/examples/assets/referendum.csv
geoviews/examples/assets/results.json
geoviews/examples/assets/boundaries/boundaries.dbf
geoviews/examples/assets/boundaries/boundaries.shp
geoviews/examples/assets/boundaries/boundaries.shx
geoviews/examples/gallery/bokeh/airport_graph.ipynb
geoviews/examples/gallery/bokeh/brexit_choropleth.ipynb
geoviews/examples/gallery/bokeh/city_populations_2050.ipynb
geoviews/examples/gallery/bokeh/filled_contours.ipynb
geoviews/examples/gallery/bokeh/great_circle.ipynb
geoviews/examples/gallery/bokeh/katrina_track.ipynb
geoviews/examples/gallery/bokeh/new_york_boroughs.ipynb
geoviews/examples/gallery/bokeh/orthographic_vectorfield.ipynb
geoviews/examples/gallery/bokeh/tile_sources.ipynb
geoviews/examples/gallery/bokeh/trimesh_uk.ipynb
geoviews/examples/gallery/bokeh/vectorfield_example.ipynb
geoviews/examples/gallery/bokeh/wind_barbs_example.ipynb
geoviews/examples/gallery/bokeh/world_population.ipynb
geoviews/examples/gallery/bokeh/xarray_image.ipynb
geoviews/examples/gallery/bokeh/xarray_quadmesh.ipynb
geoviews/examples/gallery/matplotlib/airport_graph.ipynb
geoviews/examples/gallery/matplotlib/brexit_choropleth.ipynb
geoviews/examples/gallery/matplotlib/city_population.ipynb
geoviews/examples/gallery/matplotlib/filled_contours.ipynb
geoviews-1.15.0.dist-info/METADATA
geoviews-1.15.0.dist-info/WHEEL
geoviews-1.15.0.dist-info/entry_points.txt
geoviews-1.15.0.dist-info/licenses/LICENSE
geoviews-1.15.0.dist-info/RECORD
