Metadata-Version: 2.4
Name: geoviews
Version: 1.15.0
Summary: GeoViews is a Python library that makes it easy to explore and visualize geographical, meteorological, and oceanographic datasets, such as those used in weather, climate, and remote sensing research.
Project-URL: Issue Tracker, https://github.com/holoviz/geoviews/issues?q=sort%3Aupdated-desc+is%3Aissue+is%3Aopen
Project-URL: Blog, https://blog.holoviz.org/
Project-URL: Changelog, https://github.com/holoviz/geoviews/blob/main/CHANGELOG.md
Project-URL: Discord, https://discord.gg/AXRHnJU6sP
Project-URL: Discourse, https://discourse.holoviz.org
Project-URL: Documentation, https://geoviews.org/
Project-URL: Funding, https://opencollective.com/holoviz
Project-URL: HoloViz, https://holoviz.org/
Project-URL: Homepage, https://geoviews.org
Project-URL: Repository, https://github.com/holoviz/geoviews
Author-email: HoloViz developers <developers@holoviz.org>
Maintainer-email: HoloViz developers <developers@holoviz.org>
License-Expression: BSD-3-Clause
License-File: LICENSE
Classifier: Development Status :: 5 - Production/Stable
Classifier: Framework :: Matplotlib
Classifier: Intended Audience :: Developers
Classifier: Intended Audience :: Science/Research
Classifier: Natural Language :: English
Classifier: Operating System :: OS Independent
Classifier: Programming Language :: Python :: 3.10
Classifier: Programming Language :: Python :: 3.11
Classifier: Programming Language :: Python :: 3.12
Classifier: Programming Language :: Python :: 3.13
Classifier: Programming Language :: Python :: 3.14
Classifier: Topic :: Scientific/Engineering
Classifier: Topic :: Software Development :: Libraries
Requires-Python: >=3.10
Requires-Dist: bokeh>=3.8.0
Requires-Dist: cartopy>=0.18.0
Requires-Dist: holoviews>=1.16.0
Requires-Dist: numpy
Requires-Dist: packaging
Requires-Dist: panel>=1.0.0
Requires-Dist: param<3.0,>=1.9.3
Requires-Dist: pyproj
Requires-Dist: shapely>=1.8.0
Requires-Dist: xyzservices
Provides-Extra: recommended
Requires-Dist: datashader; extra == 'recommended'
Requires-Dist: geopandas; extra == 'recommended'
Requires-Dist: matplotlib>2.2; extra == 'recommended'
Requires-Dist: netcdf4; extra == 'recommended'
Requires-Dist: pandas; extra == 'recommended'
Requires-Dist: pooch; extra == 'recommended'
Requires-Dist: pyct; extra == 'recommended'
Requires-Dist: scipy; extra == 'recommended'
Requires-Dist: xarray; extra == 'recommended'
